nordata/__init__.py
nordata/_boto.py
nordata/_redshift.py
nordata/_s3.py
nordata-0.2.3.dist-info/LICENSE
nordata-0.2.3.dist-info/WHEEL
nordata-0.2.3.dist-info/METADATA
nordata-0.2.3.dist-info/RECORD
