Metadata-Version: 2.1
Name: nordata
Version: 0.2.3
Summary: Convenience wrappers for connecting to AWS S3 and Redshift
Home-page: https://github.com/Nordstrom/nordata
License: UNKNOWN
Author: Nick Buker
Author-email: nick.buker@nordstrom.net
Requires-Python: >=3.6,<4
Classifier: Development Status :: 3 - Alpha
Classifier: License :: OSI Approved :: Apache Software License
Classifier: Programming Language :: Python :: 3.6
Classifier: Programming Language :: Python :: 3.7
Classifier: Programming Language :: Python :: 3.8
Requires-Dist: boto3 >=1.9.38
Requires-Dist: psycopg2-binary >=2.7.5
